spotifyunlock/__init__.py
spotifyunlock/__main__.py
spotifyunlock/main.py
spotifyunlock-0.0.1.dist-info/METADATA
spotifyunlock-0.0.1.dist-info/WHEEL
spotifyunlock-0.0.1.dist-info/top_level.txt
spotifyunlock-0.0.1.dist-info/RECORD
