Metadata-Version: 2.1
Name: spotifyunlock
Version: 0.0.1
Summary: Unlock Spotify Premium for free.
Author: Team Illusion
Classifier: Development Status :: 1 - Planning
Classifier: Intended Audience :: Developers
Classifier: Programming Language :: Python :: 3
Classifier: Operating System :: Unix
Classifier: Operating System :: MacOS :: MacOS X
Classifier: Operating System :: Microsoft :: Windows
Requires-Dist: requests
Requires-Dist: illusioncolor
Requires-Dist: illusionanime
